ataxx/__init__.py
ataxx/draw.py
ataxx/pgn.py
ataxx/players.py
ataxx/process.py
ataxx/socket.py
ataxx/uai.py
ataxx/zobrist.py
ataxx-2.2.0.dist-info/LICENSE
ataxx-2.2.0.dist-info/METADATA
ataxx-2.2.0.dist-info/WHEEL
ataxx-2.2.0.dist-info/top_level.txt
ataxx-2.2.0.dist-info/RECORD
