Metadata-Version: 2.1
Name: ataxx
Version: 2.2.0
Summary: python-ataxx is written in Python 3 and supports basic features such as move generation, move validation, engine communication, and board printing.
Home-page: https://github.com/kz04px/python-ataxx
License: MIT
Keywords: ataxx
Platform: UNKNOWN
License-File: LICENSE
Provides-Extra: draw
Requires-Dist: Pillow ; extra == 'draw'
